kirjava/__init__.py
kirjava/_argument.py
kirjava/_helper.py
kirjava/_struct.py
kirjava/constants.py
kirjava/environment.py
kirjava/error.py
kirjava/skeleton.py
kirjava/source.py
kirjava/verifier.py
kirjava/version.py
kirjava/abc/__init__.py
kirjava/abc/class_.py
kirjava/abc/constant.py
kirjava/abc/field.py
kirjava/abc/graph.py
kirjava/abc/method.py
kirjava/abc/source.py
kirjava/analysis/__init__.py
kirjava/analysis/_generify.py
kirjava/analysis/_trace.py
kirjava/analysis/frame.py
kirjava/analysis/graph/__init__.py
kirjava/analysis/graph/_asm.py
kirjava/analysis/graph/_dis.py
kirjava/analysis/graph/block.py
kirjava/analysis/graph/debug.py
kirjava/analysis/graph/edge.py
kirjava/classfile/__init__.py
kirjava/classfile/_constant.py
kirjava/classfile/_instructions.py
kirjava/classfile/_provider.py
kirjava/classfile/members.py
kirjava/classfile/attributes/__init__.py
kirjava/classfile/attributes/class_.py
kirjava/classfile/attributes/code.py
kirjava/classfile/attributes/field.py
kirjava/classfile/attributes/method.py
kirjava/classfile/attributes/shared.py
kirjava/instructions/__init__.py
kirjava/instructions/arithmetic.py
kirjava/instructions/array.py
kirjava/instructions/constant.py
kirjava/instructions/conversion.py
kirjava/instructions/field.py
kirjava/instructions/flow.py
kirjava/instructions/invoke.py
kirjava/instructions/local.py
kirjava/instructions/new.py
kirjava/instructions/other.py
kirjava/instructions/stack.py
kirjava/jarfile/__init__.py
kirjava/jarfile/abc.py
kirjava/jarfile/cdfh.py
kirjava/jarfile/eocd.py
kirjava/jarfile/lfh.py
kirjava/types/__init__.py
kirjava/types/descriptor.py
kirjava/types/signature.py
kirjava_jvm-0.1.8.dist-info/LICENSE.txt
kirjava_jvm-0.1.8.dist-info/METADATA
kirjava_jvm-0.1.8.dist-info/WHEEL
kirjava_jvm-0.1.8.dist-info/top_level.txt
kirjava_jvm-0.1.8.dist-info/RECORD
