Metadata-Version: 2.1
Name: kirjava-jvm
Version: 0.1.8
Summary: A Java bytecode library for Python.
Home-page: https://github.com/notiska/kirjava
Author-email: node3113@gmail.com
License: GPL-3.0
Keywords: java,jvm,bytecode,assembler,disassembler
Classifier: License :: OSI Approved :: GNU General Public License v3 (GPLv3)
Classifier: Development Status :: 4 - Beta
Classifier: Intended Audience :: Developers
Classifier: Topic :: File Formats
Classifier: Topic :: Software Development
Classifier: Topic :: Software Development :: Assemblers
Classifier: Topic :: Software Development :: Code Generators
Classifier: Topic :: Software Development :: Disassemblers
Classifier: Topic :: Software Development :: Libraries :: Java Libraries
Classifier: Operating System :: OS Independent
Classifier: Programming Language :: Python
Classifier: Programming Language :: Python :: 3.10
Classifier: Programming Language :: Python :: 3.11
Classifier: Programming Language :: Python :: 3.12
License-File: LICENSE.txt
